config/__init__.py
config/wsgi.py
config/settings/__init__.py
config/settings/base.py
config/settings/local.py
config/settings/production.py
config/settings/staging.py
config/settings/test.py
wtfix/__init__.py
wtfix/conftest.py
wtfix/pipeline.py
wtfix/apps/__init__.py
wtfix/apps/admin.py
wtfix/apps/base.py
wtfix/apps/brokers.py
wtfix/apps/parsers.py
wtfix/apps/sessions.py
wtfix/apps/store.py
wtfix/apps/utils.py
wtfix/apps/wire.py
wtfix/apps/api/__init__.py
wtfix/apps/api/rest.py
wtfix/apps/api/utils.py
wtfix/apps/api/tests/__init__.py
wtfix/apps/api/tests/conftest.py
wtfix/apps/api/tests/test_rest.py
wtfix/apps/tests/__init__.py
wtfix/apps/tests/conftest.py
wtfix/apps/tests/test_admin.py
wtfix/apps/tests/test_base.py
wtfix/apps/tests/test_parsers.py
wtfix/apps/tests/test_sessions.py
wtfix/apps/tests/test_store.py
wtfix/apps/tests/test_wire.py
wtfix/conf/__init__.py
wtfix/conf/global_settings.py
wtfix/core/__init__.py
wtfix/core/decoders.py
wtfix/core/encoders.py
wtfix/core/exceptions.py
wtfix/core/klass.py
wtfix/core/utils.py
wtfix/core/tests/__init__.py
wtfix/core/tests/conftest.py
wtfix/core/tests/test_decoders.py
wtfix/core/tests/test_encoders.py
wtfix/core/tests/test_utils.py
wtfix/message/__init__.py
wtfix/message/admin.py
wtfix/message/collections.py
wtfix/message/field.py
wtfix/message/message.py
wtfix/message/tests/__init__.py
wtfix/message/tests/conftest.py
wtfix/message/tests/test_collections.py
wtfix/message/tests/test_field.py
wtfix/message/tests/test_message.py
wtfix/protocol/__init__.py
wtfix/protocol/contextlib.py
wtfix/protocol/message_types.py
wtfix/protocol/spec.py
wtfix/protocol/tags.py
wtfix/protocol/fix/__init__.py
wtfix/protocol/fix/spec.py
wtfix/protocol/fix/_44/__init__.py
wtfix/protocol/fix/_44/message_types.py
wtfix/protocol/fix/_44/spec.py
wtfix/protocol/fix/_44/tags.py
wtfix/protocol/tests/__init__.py
wtfix/protocol/tests/test_spec.py
wtfix/tests/__init__.py
wtfix/tests/conftest.py
wtfix/tests/test_pipeline.py
wtfix-0.16.2.dist-info/COPYING
wtfix-0.16.2.dist-info/COPYING.LESSER
wtfix-0.16.2.dist-info/METADATA
wtfix-0.16.2.dist-info/WHEEL
wtfix-0.16.2.dist-info/top_level.txt
wtfix-0.16.2.dist-info/RECORD
