Metadata-Version: 2.1
Name: wtfix
Version: 0.16.2
Summary: The Pythonic Financial Information eXchange (FIX) client that you have been looking for.
Home-page: https://github.com/jcass77/WTFIX
Author: John Cass
Author-email: john.cass77@gmail.com
License: UNKNOWN
Project-URL: Bug Reports, https://github.com/jcass77/WTFIX/issues
Project-URL: Source, https://github.com/jcass77/WTFIX/
Keywords: FIX financial information exchange
Platform: UNKNOWN
Classifier: Development Status :: 4 - Beta
Classifier: Framework :: AsyncIO
Classifier: Programming Language :: Python :: 3.8
Classifier: Programming Language :: Python :: 3.9
Classifier: License :: OSI Approved :: GNU Lesser General Public License v3 (LGPLv3)
Classifier: Operating System :: OS Independent
Classifier: Intended Audience :: Financial and Insurance Industry
Requires-Python: >=3.8
Requires-Dist: python-dotenv (>=0.10.3)
Requires-Dist: flask-restful (>=0.3.7)
Requires-Dist: requests (>=2.22)
Requires-Dist: gunicorn (>=19.9)
Requires-Dist: aioredis (>=1.3)
